jupyter_containers/__init__.py
jupyter_containers/_version.py
jupyter_containers/handlers.py
jupyter_containers/tests/__init__.py
jupyter_containers/tests/test_handlers.py
jupyter_containers-0.0.3.data/data/etc/jupyter/jupyter_notebook_config.d/jupyter_containers.json
jupyter_containers-0.0.3.data/data/etc/jupyter/jupyter_server_config.d/jupyter_containers.json
jupyter_containers-0.0.3.data/data/share/jupyter/labextensions/@datalayer/jupyter-containers/build_log.json
jupyter_containers-0.0.3.data/data/share/jupyter/labextensions/@datalayer/jupyter-containers/package.json
jupyter_containers-0.0.3.data/data/share/jupyter/labextensions/@datalayer/jupyter-containers/schemas/@datalayer/jupyter-containers/package.json.orig
jupyter_containers-0.0.3.data/data/share/jupyter/labextensions/@datalayer/jupyter-containers/schemas/@datalayer/jupyter-containers/plugin.json
jupyter_containers-0.0.3.data/data/share/jupyter/labextensions/@datalayer/jupyter-containers/static/docker_lib_index_js.192b5eb2526efd7a9a9e.js
jupyter_containers-0.0.3.data/data/share/jupyter/labextensions/@datalayer/jupyter-containers/static/docker_lib_index_js.192b5eb2526efd7a9a9e.js.map
jupyter_containers-0.0.3.data/data/share/jupyter/labextensions/@datalayer/jupyter-containers/static/lib_index_js.5dc5b4be8085ea61d008.js
jupyter_containers-0.0.3.data/data/share/jupyter/labextensions/@datalayer/jupyter-containers/static/lib_index_js.5dc5b4be8085ea61d008.js.map
jupyter_containers-0.0.3.data/data/share/jupyter/labextensions/@datalayer/jupyter-containers/static/remoteEntry.96922a8aa5a003c79d1f.js
jupyter_containers-0.0.3.data/data/share/jupyter/labextensions/@datalayer/jupyter-containers/static/remoteEntry.96922a8aa5a003c79d1f.js.map
jupyter_containers-0.0.3.data/data/share/jupyter/labextensions/@datalayer/jupyter-containers/static/style.js
jupyter_containers-0.0.3.data/data/share/jupyter/labextensions/@datalayer/jupyter-containers/static/style_index_js.9fb9d555d3bab4bec2b9.js
jupyter_containers-0.0.3.dist-info/METADATA
jupyter_containers-0.0.3.dist-info/WHEEL
jupyter_containers-0.0.3.dist-info/licenses/LICENSE
jupyter_containers-0.0.3.dist-info/RECORD
